setup.py
behave_pytest/__init__.py
behave_pytest/hook.py
behave_pytest.egg-info/PKG-INFO
behave_pytest.egg-info/SOURCES.txt
behave_pytest.egg-info/dependency_links.txt
behave_pytest.egg-info/requires.txt
behave_pytest.egg-info/top_level.txt