Metadata-Version: 1.1
Name: behave-pytest
Version: 0.1.1
Summary: Integrates pytest asserts with behave
Home-page: https://github.com/ribozz/behave-pytest
Author: Alex Rudakov
Author-email: ribozz@gmail.com
License: UNKNOWN
Platform: UNKNOWN
Classifier: Development Status :: 2 - Pre-Alpha
Classifier: Programming Language :: Python
Classifier: Programming Language :: Python :: 2
Classifier: Programming Language :: Python :: 2.7
Classifier: Programming Language :: Python :: 3
Classifier: Programming Language :: Python :: 3.4
